chi_mailer/Qi.py
chi_mailer/__init__.py
chi_mailer/contacts.txt
chi_mailer/messages.txt
chi_mailer-1.0.dist-info/LICENSE
chi_mailer-1.0.dist-info/METADATA
chi_mailer-1.0.dist-info/WHEEL
chi_mailer-1.0.dist-info/top_level.txt
chi_mailer-1.0.dist-info/RECORD
