Metadata-Version: 2.1
Name: chi-mailer
Version: 1.0
Summary: python bulk/mass mailer package
Home-page: https://github.com/stevemats/chi_mailer
Author: Stevemats & fkinaro
Author-email: stevematindi@gmail.com
License: BSD License
Platform: UNKNOWN
Classifier: Environment :: Console
Classifier: Intended Audience :: Developers
Classifier: Programming Language :: Python :: 3
Classifier: License :: OSI Approved :: MIT License
Classifier: Operating System :: OS Independent
Classifier: Topic :: Software Development :: Libraries :: Python Modules
Classifier: Topic :: Utilities
